backups/__init__.py
backups/run_scanner.py
backups/scanner.py
src/__init__.py
src/run_scanner.py
src/scanner.py
tests/__init__.py
tests/test_scanner.py
AcSecurity-1.2.1.dist-info/METADATA
AcSecurity-1.2.1.dist-info/WHEEL
AcSecurity-1.2.1.dist-info/entry_points.txt
AcSecurity-1.2.1.dist-info/top_level.txt
AcSecurity-1.2.1.dist-info/RECORD
