Metadata-Version: 2.1
Name: AcSecurity
Version: 1.2.1
Summary: A security scanner for applications.
Home-page: https://github.com/austincabler13/AcSecurity
Author: Austin Cabler
Author-email: austin_cabler@icloud.com
Classifier: Programming Language :: Python :: 3
Classifier: License :: OSI Approved :: MIT License
Classifier: Operating System :: OS Independent
Requires-Python: >=3.12
Requires-Dist: pip-audit
Requires-Dist: pylint
Requires-Dist: argparse
Requires-Dist: pytest
